date_time_handler/__init__.py
date_time_handler/main.py
date_time_handler-0.0.0.21.dist-info/LICENSE
date_time_handler-0.0.0.21.dist-info/METADATA
date_time_handler-0.0.0.21.dist-info/WHEEL
date_time_handler-0.0.0.21.dist-info/top_level.txt
date_time_handler-0.0.0.21.dist-info/RECORD
