Metadata-Version: 2.1
Name: date-time-handler
Version: 0.0.0.21
Summary: Robust date-time formatter with implicit time-zone conversion, wraps datetime and pytz
Home-page: https://github.com/jmsimons/date_time_handler
Author: Jared Simons
Author-email: jmsimons@lcmail.lcsc.edu
License: UNKNOWN
Platform: UNKNOWN
Requires-Dist: time
Requires-Dist: datetime
Requires-Dist: python-dateutil
Requires-Dist: pytz
